odoo_orm/__init__.py
odoo_orm/connection.py
odoo_orm/errors.py
odoo_orm/orm.py
odoo_orm-3.0.0.dist-info/WHEEL
odoo_orm-3.0.0.dist-info/METADATA
odoo_orm-3.0.0.dist-info/RECORD
