Metadata-Version: 2.4
Name: odoo-orm
Version: 3.0.0
Summary: A kind of Python ORM for Odoo XML-RPC API inspired by Django ORM.
Author: mistiru
Author-email: mistiru <dev@mistiru.me>
License-Expression: MIT
Classifier: Programming Language :: Python :: 3
Classifier: Programming Language :: Python :: 3.9
Classifier: Programming Language :: Python :: 3.10
Classifier: Programming Language :: Python :: 3.11
Classifier: Programming Language :: Python :: 3.12
Requires-Python: >=3.9
Project-URL: source, https://github.com/mistiru/odoo-orm
